AUTHORS.rst
CONTRIBUTING.rst
HISTORY.rst
LICENSE
MANIFEST.in
README.rst
setup.cfg
setup.py
django_web3auth.egg-info/PKG-INFO
django_web3auth.egg-info/SOURCES.txt
django_web3auth.egg-info/dependency_links.txt
django_web3auth.egg-info/not-zip-safe
django_web3auth.egg-info/requires.txt
django_web3auth.egg-info/top_level.txt
web3auth/__init__.py
web3auth/admin.py
web3auth/apps.py
web3auth/backend.py
web3auth/forms.py
web3auth/models.py
web3auth/settings.py
web3auth/tests.py
web3auth/urls.py
web3auth/utils.py
web3auth/views.py
web3auth/static/web3auth/css/web3auth.css
web3auth/static/web3auth/js/web3auth.js
web3auth/templates/web3auth/base.html
web3auth/templates/web3auth/signup.html